recpack/__init__.py
recpack/util.py
recpack/algorithms/__init__.py
recpack/algorithms/base.py
recpack/algorithms/baseline.py
recpack/algorithms/bprmf.py
recpack/algorithms/ease.py
recpack/algorithms/factorization.py
recpack/algorithms/factorization_item_similarity.py
recpack/algorithms/gru4rec.py
recpack/algorithms/kunn.py
recpack/algorithms/loss_functions.py
recpack/algorithms/mult_vae.py
recpack/algorithms/nearest_neighbour.py
recpack/algorithms/p2v.py
recpack/algorithms/p2v_clustered.py
recpack/algorithms/rec_vae.py
recpack/algorithms/samplers.py
recpack/algorithms/sequential_rules.py
recpack/algorithms/slim.py
recpack/algorithms/stan.py
recpack/algorithms/stopping_criterion.py
recpack/algorithms/util.py
recpack/algorithms/wmf.py
recpack/algorithms/experimental/__init__.py
recpack/algorithms/experimental/ease_xy.py
recpack/algorithms/experimental/shared_account.py
recpack/algorithms/time_aware_item_knn/__init__.py
recpack/algorithms/time_aware_item_knn/base.py
recpack/algorithms/time_aware_item_knn/decay_functions.py
recpack/algorithms/time_aware_item_knn/ding_2005.py
recpack/algorithms/time_aware_item_knn/hermann_2010.py
recpack/algorithms/time_aware_item_knn/lee_2007.py
recpack/algorithms/time_aware_item_knn/liu_2010.py
recpack/algorithms/time_aware_item_knn/liu_2012.py
recpack/algorithms/time_aware_item_knn/vaz_2013.py
recpack/algorithms/time_aware_item_knn/xia_2010.py
recpack/datasets/__init__.py
recpack/datasets/adressa.py
recpack/datasets/base.py
recpack/datasets/cite_u_like.py
recpack/datasets/cosmetics_shop.py
recpack/datasets/dummy_dataset.py
recpack/datasets/globo.py
recpack/datasets/million_song_dataset.py
recpack/datasets/movielens.py
recpack/datasets/netflix.py
recpack/datasets/recsys_challenge.py
recpack/datasets/retail_rocket.py
recpack/datasets/thirty_music_sessions.py
recpack/matrix/__init__.py
recpack/matrix/interaction_matrix.py
recpack/matrix/util.py
recpack/metrics/__init__.py
recpack/metrics/base.py
recpack/metrics/coverage.py
recpack-0.3.6.dist-info/LICENSE
recpack-0.3.6.dist-info/METADATA
recpack-0.3.6.dist-info/WHEEL
recpack-0.3.6.dist-info/top_level.txt
recpack-0.3.6.dist-info/RECORD
