Metadata-Version: 2.1
Name: recpack
Version: 0.3.6
Summary: Python package for Top-N recommendation based on implicit feedback data.
Home-page: https://gitlab.com/recpack-maintainers/recpack
Project-URL: Documentation, https://recpack.froomle.ai
Requires-Python: >=3.8
License-File: LICENSE
Requires-Dist: numpy ==1.*,>=1.21.2
Requires-Dist: scipy ==1.*,>=1.6.0
Requires-Dist: scikit-learn ==1.*,>=1.1.1
Requires-Dist: pandas ==2.*,>=2.1.4
Requires-Dist: PyYAML ==6.*,>=6.0.1
Requires-Dist: torch ==2.*,>=2.1.1
Requires-Dist: tqdm ==4.*,>=4.46.0
Requires-Dist: hyperopt ==0.2.*,>=0.2.7
Provides-Extra: doc
Requires-Dist: sphinx ==4.* ; extra == 'doc'
Requires-Dist: sphinx-rtd-theme ==1.* ; extra == 'doc'
Provides-Extra: test
Requires-Dist: pytest ==6.*,>=6.2.4 ; extra == 'test'
Requires-Dist: pytest-cov ==2.*,>=2.12.1 ; extra == 'test'
